{
    "usuarios": {
        "Priscila19": {
            "username": "Priscila19",
            "password_hash": "$2b$12$Uz10TEpIBz9Cjt.Kippq7uHWNd2.5j/Tz9rdWpw4vf3Q9Tir6GS1a",
            "datos_personales": {
                "nombre": "Priscila",
                "edad": "19",
                "email": "extrapris835@gmail.com"
            },
            "intereses": {},
            "privacidad": {},
            "solicitudes_enviadas": [],
            "solicitudes_recibidas": [],
            "avatar": "default.png",
            "fotos": [],
            "verificado": true
        },
        "Jey19": {
            "username": "Jey19",
            "password_hash": "$2b$12$BtR3h2jwRd7W6C5hfRLAruo9w6M4oQwboKHqTfq7UHg4UnBNRN63G",
            "datos_personales": {
                "nombre": "Jeyni",
                "edad": "19",
                "email": "pjulieths@uamv.edu.ni"
            },
            "intereses": {},
            "privacidad": {},
            "solicitudes_enviadas": [],
            "solicitudes_recibidas": [],
            "avatar": "default.png",
            "fotos": [
                {
                    "filename": "Jey19_Mesa_de_trabajo_79.png",
                    "descripcion": "Te invito a un caf\u00e9",
                    "autor": "Jey19",
                    "comentarios": [],
                    "likes": [
                        "Priscila19"
                    ]
                }
            ],
            "verificado": false
        },
        "JeyOrozco20": {
            "username": "JeyOrozco20",
            "password_hash": "$2b$12$yzWRz41CGZeNZW1W3PJPtO2SvoXW9esqkijvHPLWlX4ABD7QR1jDK",
            "datos_personales": {
                "nombre": "Jeyni",
                "edad": "19",
                "email": "pjulieths@uamv.edu.ni"
            },
            "intereses": {},
            "privacidad": {},
            "solicitudes_enviadas": [],
            "solicitudes_recibidas": [],
            "avatar": "default.png",
            "fotos": [],
            "verificado": false
        }
    },
    "amistades": [
        [
            "Priscila19",
            "Jey19"
        ]
    ]
}